dgscrna/__init__.py
dgscrna/core/__init__.py
dgscrna/core/clustering.py
dgscrna/core/deep_learning.py
dgscrna/core/marker_scoring.py
dgscrna/core/preprocessing.py
dgscrna/core/utils.py
dgscrna/models/__init__.py
dgscrna/models/deep_model.py
dgscrna-1.1.dist-info/licenses/LICENSE
dgscrna-1.1.dist-info/METADATA
dgscrna-1.1.dist-info/WHEEL
dgscrna-1.1.dist-info/top_level.txt
dgscrna-1.1.dist-info/RECORD
