Metadata-Version: 2.4
Name: dgscrna
Version: 1.1
Summary: A Python package for single-cell RNA-seq cell type annotation using marker-based scoring and deep learning
Author-email: Yimin Liu <yiminliu.career@gmail.com>
License: GPL-3.0
Project-URL: Homepage, https://github.com/yourusername/DGscRNA
Project-URL: Repository, https://github.com/yourusername/DGscRNA.git
Project-URL: Bug Tracker, https://github.com/yourusername/DGscRNA/issues
Keywords: single-cell,RNA-seq,cell-type,annotation,bioinformatics
Classifier: Development Status :: 3 - Alpha
Classifier: Intended Audience :: Science/Research
Classifier: License :: OSI Approved :: GNU General Public License v3 (GPLv3)
Classifier: Operating System :: OS Independent
Classifier: Programming Language :: Python :: 3
Classifier: Programming Language :: Python :: 3.8
Classifier: Programming Language :: Python :: 3.9
Classifier: Programming Language :: Python :: 3.10
Classifier: Programming Language :: Python :: 3.11
Classifier: Topic :: Scientific/Engineering :: Bio-Informatics
Requires-Python: >=3.8
License-File: LICENSE
Requires-Dist: numpy>=1.21.0
Requires-Dist: scipy>=1.7.0
Requires-Dist: pandas>=1.3.0
Requires-Dist: scanpy>=1.9.0
Requires-Dist: anndata>=0.8.0
Requires-Dist: scikit-learn>=1.0.0
Requires-Dist: torch>=1.9.0
Requires-Dist: torchmetrics>=0.7.0
Requires-Dist: hdbscan>=0.8.0
Requires-Dist: leidenalg>=0.8.0
Requires-Dist: harmonypy>=0.0.5
Requires-Dist: matplotlib>=3.5.0
Requires-Dist: seaborn>=0.11.0
Requires-Dist: tqdm>=4.62.0
Requires-Dist: joblib>=1.1.0
Provides-Extra: dev
Requires-Dist: pytest>=6.0; extra == "dev"
Requires-Dist: pytest-cov>=2.0; extra == "dev"
Requires-Dist: black>=21.0; extra == "dev"
Requires-Dist: flake8>=3.8; extra == "dev"
Requires-Dist: mypy>=0.800; extra == "dev"
Requires-Dist: bump2version>=1.0.0; extra == "dev"
Dynamic: license-file
